<?xml version="1.0"?>
<GUI Try="Try" GridLines="8" EditCol="0|0|0" RowColor="15790320|16777215|12648447|11861980|16777152|16761087" IndicatorColor="255|15790320|16711680|0" ThemeFile="1" Class="FitLinear" ClassOptionName="FitLinear" AdvanThemeFile="FitLinear" ExecMode="1" ComboChanged="65"><AutoUpdate NodeID="13" Label="Recalculate" DataID="15" Enable="1" DB_CTRL_ID="6000">2</AutoUpdate><Separator NodeID="77" DB_CTRL_ID="6002"/><InputData NodeID="44" Label="Input Data" DataID="2097163" Branch="1" DataMode="3" Use="0" BranchCombo="Independent Fit - Consolidated Report|Independent Fit - Separate Report|Concatenate Fit|Global Fit" ActionFilterTags="FitCurve" HandlerRC="333812488" InteractiveOptions="32" DataRules="5505024" ChangeParam="0" DB_CTRL_ID="6003"><Range1 NodeID="39" PlotObjUID="852"><X NodeID="35">[Book3]Price__n=10000_avgdeg=4Distribut!A</X><Y NodeID="35">[Book3]Price__n=10000_avgdeg=4Distribut!B</Y></Range1></InputData><Order NodeID="17" Label="Polynomial Order" DataID="194" Show="0" DB_CTRL_ID="6004">2.</Order><Fit NodeID="268435456" Label="Fit Options" DataID="2097205" Branch="2049" DB_CTRL_ID="6006"><ErrBarWeight NodeID="13" Label="Errors as Weight" DataID="205" Handler="328559184" DB_CTRL_ID="6007" Enable="0">2.</ErrBarWeight><YWeight NodeID="13" Label="Y Weighting Method" DataID="1300" Show="0" DB_CTRL_ID="6009">0.</YWeight><XWeight NodeID="13" Label="X Weighting Method" DataID="1305" Show="0" DB_CTRL_ID="6011">0.</XWeight><FixIntercept NodeID="10" Label="Fix Intercept" DataID="225" Handler="328559408" DB_CTRL_ID="6013">0.</FixIntercept><FixInterceptAt NodeID="14" Label="Fix Intercept at" DataID="230" DB_CTRL_ID="6015" Enable="0">0.</FixInterceptAt><FixSlope NodeID="10" Label="Fix Slope" DataID="195" Handler="328557392" DB_CTRL_ID="6017">0.</FixSlope><FixSlopeAt NodeID="14" Label="Fix Slope at" DataID="200" DB_CTRL_ID="6019" Enable="0">1.</FixSlopeAt><UseReducedChiSq NodeID="10" Label="Use Reduced Chi-Sqr" DataID="210" DB_CTRL_ID="6021" Enable="0">1</UseReducedChiSq><ApparentFit NodeID="10" Label="Apparent Fit" DataID="220" Handler="328545744" DB_CTRL_ID="6023" Enable="1">0.</ApparentFit></Fit><Quantities NodeID="268435456" Label="Quantities to Compute" DataID="2097170" Branch="2048" DB_CTRL_ID="6025"><Parameters NodeID="268435456" Label="Fit Parameters" DataID="2097169" Branch="2048" DB_CTRL_ID="6026"><Value NodeID="10" Label="Value" DataID="320" DB_CTRL_ID="6027">1.</Value><Fix NodeID="10" Label="Fixed or Vary" DataID="322" Show="0" DB_CTRL_ID="6029">0.</Fix><Error NodeID="10" Label="Standard Error" DataID="321" DB_CTRL_ID="6031">1.</Error><LCL NodeID="10" Label="LCL" DataID="330" HandlerRC="328542832" DB_CTRL_ID="6033">0.</LCL><UCL NodeID="10" Label="UCL" DataID="331" HandlerRC="328542832" DB_CTRL_ID="6035">0.</UCL><Confidence NodeID="14" Label="Confidence Level for Parameters(%)" DataID="215" HandlerRC="328542832" DB_CTRL_ID="6037" Enable="0">95.</Confidence><tValue NodeID="10" Label="t-Value" DataID="325" DB_CTRL_ID="6039">0.</tValue><Prob NodeID="10" Label="Prob&gt;|t|" DataID="334" DB_CTRL_ID="6041">0.</Prob><Dependency NodeID="10" Label="Dependency" DataID="337" Show="0" DB_CTRL_ID="6043">0.</Dependency><ConfInterval NodeID="10" Label="CI Half-Width" DataID="338" DB_CTRL_ID="6045">0.</ConfInterval></Parameters><Statistics NodeID="268435456" Label="Fit Statistics" DataID="2097168" Branch="2048" DB_CTRL_ID="6047"><N NodeID="10" Label="Number of Points" DataID="350" DB_CTRL_ID="6048">1.</N><DOF NodeID="10" Label="Degrees of Freedom" DataID="351" DB_CTRL_ID="6050">1.</DOF><ReducedChiSq NodeID="10" Label="Reduced Chi-Sqr" DataID="366" Show="0" DB_CTRL_ID="6052">0</ReducedChiSq><Rvalue NodeID="10" Label="R Value" DataID="352" DB_CTRL_ID="6054">0.</Rvalue><SSR NodeID="10" Label="Residual Sum of Squares" DataID="367" DB_CTRL_ID="6056">1.</SSR><Correlation NodeID="10" Label="Correlation" DataID="370" Show="0" DB_CTRL_ID="6058">0.</Correlation><RSqCOD NodeID="10" Label="R-Square(COD)" DataID="355" DB_CTRL_ID="6060">0.</RSqCOD><AdjRSq NodeID="10" Label="Adj. R-Square" DataID="356" DB_CTRL_ID="6062">1.</AdjRSq><RMSESD NodeID="10" Label="Root-MSE (SD)" DataID="360" DB_CTRL_ID="6064">0.</RMSESD><NormResiduals NodeID="10" Label="Norm of Residuals" DataID="380" DB_CTRL_ID="6066">0.</NormResiduals><NumIter NodeID="10" Label="Number of Iterations" DataID="382" Show="0" DB_CTRL_ID="6068">0.</NumIter><FitStatus NodeID="10" Label="Fit Status" DataID="384" Show="0" DB_CTRL_ID="6070">1.</FitStatus></Statistics><SummaryTable NodeID="268435456" Label="Fit Summary" DataID="342" Use="1" DB_CTRL_ID="6072"><Value NodeID="10" Label="Value" DataID="343" DB_CTRL_ID="6073">1.</Value><Error NodeID="10" Label="Standard Error" DataID="344" DB_CTRL_ID="6075">1.</Error><LCL NodeID="10" Label="LCL" DataID="345" DB_CTRL_ID="6077">0.</LCL><UCL NodeID="10" Label="UCL" DataID="346" DB_CTRL_ID="6079">0.</UCL><AdjRSq NodeID="10" Label="Adj. R-Square" DataID="347" DB_CTRL_ID="6081">1.</AdjRSq><RSqCOD NodeID="10" Label="R-Square(COD)" DataID="348" DB_CTRL_ID="6083">0.</RSqCOD><ReducedChiSq NodeID="10" Label="Reduced Chi-Sqr" DataID="349" Show="0" DB_CTRL_ID="6085">0</ReducedChiSq></SummaryTable><ANOVAtable NodeID="10" Label="ANOVA" DataID="475" DB_CTRL_ID="6087">1.</ANOVAtable><mCov NodeID="10" Label="Covariance matrix" DataID="170" DB_CTRL_ID="6089">0.</mCov><mCor NodeID="10" Label="Correlation matrix" DataID="171" DB_CTRL_ID="6091">0.</mCor></Quantities><ResAnalysis NodeID="268435456" Label="Residual Analysis" DataID="2097217" Branch="2049" DB_CTRL_ID="6093"><Regular NodeID="10" Label="Regular" DataID="3951" DB_CTRL_ID="6094">1.</Regular><Stad NodeID="10" Label="Standardized" DataID="3952" DB_CTRL_ID="6096" Enable="1">0.</Stad><Stud NodeID="10" Label="Studentized" DataID="3953" DB_CTRL_ID="6098" Enable="1">0.</Stud><StudDel NodeID="10" Label="Studentized Deleted" DataID="3954" DB_CTRL_ID="6100" Enable="1">0.</StudDel></ResAnalysis><Output NodeID="268435456" Label="Output Results" DataID="2097488" Branch="2048" DB_CTRL_ID="6102"><PlotSettings NodeID="268435456" Label="Plot Settings" Branch="1" DB_CTRL_ID="6103"><PasteResultTable NodeID="268435456" Label="Paste Result Tables to Source Graph" Use="1" DataID="940" DB_CTRL_ID="6104" Enable="1"><TableTemplate NodeID="11" Label="Template to Create Table" DataID="1549" DB_CTRL_ID="6105"/><ThemeRsltTable NodeID="11" Label="Graph Table Theme" DataID="1558" DB_CTRL_ID="6107"/></PasteResultTable><GraphNumCols NodeID="14" Label="Arrange Graphs into Columns" DataID="4000" Auto="1||1" DB_CTRL_ID="6109">1</GraphNumCols></PlotSettings><RCSheet NodeID="13" Label="Fitted Results Sheet Arrangement" DataID="1559" Enable="1" DB_CTRL_ID="6112" Show="0">0.</RCSheet><Report NodeID="268435456" Label="Output Report Tables To" DataID="2097166" Branch="2048" DB_CTRL_ID="6114"><Book NodeID="11" Label="Book" DataID="907" Handler="322773760" ReportToSrcBook="1" old_combo_val="&lt;source&gt; Book3" Enable="1" DB_CTRL_ID="6115">&lt;source&gt; Book3</Book><Sheet NodeID="11" Label="Sheet" DataID="908" Handler="322773984" Enable="0" DB_CTRL_ID="6117">&lt;new&gt;</Sheet><AddReportToResultsLog NodeID="10" Label="Results Log" DataID="928" DB_CTRL_ID="6119">0.</AddReportToResultsLog><DumpScriptWindow NodeID="10" Label="Script Window" DataID="935" DB_CTRL_ID="6121">0.</DumpScriptWindow><DumpNotesWindow NodeID="11" Label="Notes Window" DataID="936" DB_CTRL_ID="6123">&lt;none&gt;</DumpNotesWindow></Report><Data NodeID="268435456" Label="Output Fitted Values To" DataID="2097164" Branch="2049" DB_CTRL_ID="6125"><Book NodeID="11" Label="Book" DataID="903" HandlerRC="322780480" Enable="1" DB_CTRL_ID="6126">&lt;auto&gt;</Book><Sheet NodeID="11" Label="Sheet" DataID="904" HandlerRC="322780928" Enable="1" DB_CTRL_ID="6128">&lt;new&gt;</Sheet></Data><Residual NodeID="268435456" Label="Output Residuals To" DataID="2097165" DB_CTRL_ID="6130"><Book NodeID="11" Label="Book" DataID="901" Handler="322774208" Enable="1" DB_CTRL_ID="6131">&lt;fittedvalue&gt;</Book><Sheet NodeID="11" Label="Sheet" DataID="902" Handler="322774432" Enable="1" DB_CTRL_ID="6133">&lt;fittedvalue&gt;</Sheet></Residual><FindXY NodeID="268435456" Label="Output Find Specific X/Y Tables" DataID="2097167" DB_CTRL_ID="6135" Branch="2" Enable="0"><Book NodeID="11" Label="Book" DataID="926" Handler="322774880" Enable="1" DB_CTRL_ID="6136">&lt;fittedvalue&gt;</Book><Sheet NodeID="11" Label="Sheet" DataID="927" Handler="322774656" Enable="1" DB_CTRL_ID="6138">&lt;new&gt;</Sheet></FindXY><Create NodeID="268435456" Label="Optional Report Tables" DataID="937" Branch="2049" DB_CTRL_ID="6140"><Notes NodeID="10" Label="Notes" DataID="1500" DB_CTRL_ID="6141">1.</Notes><InputData NodeID="10" Label="Input Data" DataID="1505" DB_CTRL_ID="6143">1.</InputData><MaskedData NodeID="10" Label="Masked Data" DataID="1510" DB_CTRL_ID="6145">1.</MaskedData><MissingData NodeID="10" Label="Missing Data" DataID="1515" DB_CTRL_ID="6147">1.</MissingData></Create><KeepSessionGraph Show="0" DB_CTRL_ID="6149">0</KeepSessionGraph></Output><Graph1 NodeID="268435456" Label="Fitted Curves Plot" DataID="1520" Use="1" RepeatID="1" DB_CTRL_ID="6151"><PlotType NodeID="13" Label="Plot Type" DataID="267" Handler="328541712" DB_CTRL_ID="6152" Show="0">0.</PlotType><PlotFit NodeID="13" Label="Plot on Original Graph" DataID="268" Handler="328560976" DB_CTRL_ID="6154" Enable="1">1</PlotFit><UpdateLegend NodeID="10" Label="Update Legend on Original Graph" DataID="269" DB_CTRL_ID="6156" Enable="1">1.</UpdateLegend><XDataType NodeID="268435456" Label="X Data Type" DataID="300" Use="0" BranchCombo="Uniform Linear|Log|Same as Input Data" Handler="328550000" Branch="1" DB_CTRL_ID="6158"><N NodeID="14" Label="Points" DataID="258" DB_CTRL_ID="6159" Enable="1">100.</N><Range NodeID="13" Label="Range" DataID="305" Handler="328555152" DB_CTRL_ID="6161" Enable="1">0.</Range><Min NodeID="14" Label="Min" DataID="280" DB_CTRL_ID="6163" Enable="1" Show="0">2.</Min><Max NodeID="14" Label="Max" DataID="282" DB_CTRL_ID="6165" Show="0" Enable="1">394.</Max><RangeMargin NodeID="14" Label="Range Margin (%)" DataID="265" DB_CTRL_ID="6167" Show="1" Enable="1">0.</RangeMargin></XDataType><ConfBands NodeID="10" Label="Confidence Bands" DataID="271" HandlerRC="328561200" DB_CTRL_ID="6169">0.</ConfBands><PredBands NodeID="10" Label="Prediction Bands" DataID="272" HandlerRC="328561200" DB_CTRL_ID="6171">0.</PredBands><Confidence NodeID="14" Label="Confidence Level for Curves(%)" DataID="275" HandlerRC="328561200" DB_CTRL_ID="6173" Enable="0">95.</Confidence><Ellipse NodeID="268435456" Label="Ellipse" Use="0" DataID="306" DB_CTRL_ID="6175"><DataPoints NodeID="11" Label="Data Points" DataID="310" DB_CTRL_ID="6176">50</DataPoints><Mean NodeID="268435456" Label="Mean" Use="1" DataID="307" DB_CTRL_ID="6178"><confidence NodeID="11" Label="Confidence Level (%)" DataID="311" Handler="328553360" DB_CTRL_ID="6179">95</confidence></Mean><Pred NodeID="268435456" Label="Prediction" Use="1" DataID="309" DB_CTRL_ID="6181"><confidence NodeID="11" Label="Confidence Level (%)" DataID="312" Handler="328553584" DB_CTRL_ID="6182">95</confidence></Pred></Ellipse></Graph1><Calibration NodeID="268435456" Label="Find Specific X/Y" DataID="2103296" DB_CTRL_ID="6184"><Custom2 NodeID="268435456" Label="Find X from Y" DataID="2103312" Use="0" RepeatID="2" Handler="328565456" NumFormat="%d" DB_CTRL_ID="6185"><Cols NodeID="17" Label="Number of X Columns" DataID="1555" DB_CTRL_ID="6186">1.</Cols></Custom2><Custom3 NodeID="268435456" Label="Find Y from X" DataID="2103376" Use="0" RepeatID="3" Handler="328565456" NumFormat="%d" DB_CTRL_ID="6188"><Cols NodeID="17" Label="Number of Y Columns" DataID="1555" DB_CTRL_ID="6189">1.</Cols></Custom3></Calibration><Residuals NodeID="268435456" Label="Residual Plots" DataID="1320" Branch="2" DB_CTRL_ID="6191"><ResType NodeID="13" Label="Residual Type" DataID="3950" DB_CTRL_ID="6192" Enable="1">0.</ResType><Graph2 NodeID="10" Label="Residual vs. Independent Plot" DataID="1521" RepeatID="2" DB_CTRL_ID="6194">1</Graph2><Graph3 NodeID="10" Label="Histogram of the Residual Plot" DataID="1522" RepeatID="3" DB_CTRL_ID="6196">0</Graph3><Graph4 NodeID="10" Label="Residual vs. Predicted Values Plot" DataID="1523" RepeatID="4" DB_CTRL_ID="6198">0</Graph4><Graph5 NodeID="10" Label="Residual vs. the Order of the Data Plot" DataID="1524" RepeatID="5" DB_CTRL_ID="6200">0</Graph5><Graph6 NodeID="10" Label="Residual Lag Plot" DataID="1525" RepeatID="6" DB_CTRL_ID="6202">0</Graph6></Residuals></GUI>
